./.gitignore
./PKG-INFO
./README.md
./pyproject.toml
./vision_agents/plugins/aws/__init__.py
./vision_agents/plugins/aws/aws_llm.py
./vision_agents/plugins/aws/aws_realtime.py
./vision_agents/plugins/aws/events.py
./vision_agents/plugins/aws/tts.py
vision_agents_plugins_aws-0.2.10.dist-info/METADATA
vision_agents_plugins_aws-0.2.10.dist-info/WHEEL
vision_agents_plugins_aws-0.2.10.dist-info/RECORD
