Metadata-Version: 2.4
Name: vision-agents-plugins-aws
Version: 0.2.10
Summary: AWS (Bedrock) LLM integration for Vision Agents
Project-URL: Documentation, https://visionagents.ai/
Project-URL: Website, https://visionagents.ai/
Project-URL: Source, https://github.com/GetStream/Vision-Agents
License-Expression: MIT
Keywords: AI,LLM,agents,aws,bedrock,voice agents
Requires-Python: >=3.12
Requires-Dist: aws-sdk-bedrock-runtime>=0.2.0
Requires-Dist: boto3>=1.42.7
Requires-Dist: onnxruntime
Requires-Dist: vision-agents
